{
  "Object": "PricebookEntry",
  "Fields": {
    "GearsetDisplayName": "Standard Price Book - SeededProduct6683",
    "GearsetExternalId__c": "IAQaMs4300000G3u10",
    "IsActive": "true",
    "UnitPrice": "6683.0",
    "UseStandardPrice": "false"
  },
  "References": [
    {
      "Name": "Pricebook2",
      "ReferencedObject": "Pricebook2",
      "ReferencedFields": {
        "GearsetExternalId__c": "StandardPriceBook"
      }
    },
    {
      "Name": "Product2",
      "ReferencedObject": "Product2",
      "ReferencedFields": {
        "GearsetExternalId__c": "KAQgCmY100000G3t10"
      }
    }
  ]
}