{
  "Object": "PricebookEntry",
  "Fields": {
    "GearsetDisplayName": "Standard Price Book - SeededProduct23779",
    "GearsetExternalId__c": "QAQKow4300000G3u10",
    "IsActive": "true",
    "UnitPrice": "23779.0",
    "UseStandardPrice": "false"
  },
  "References": [
    {
      "Name": "Pricebook2",
      "ReferencedObject": "Pricebook2",
      "ReferencedFields": {
        "GearsetExternalId__c": "StandardPriceBook"
      }
    },
    {
      "Name": "Product2",
      "ReferencedObject": "Product2",
      "ReferencedFields": {
        "GearsetExternalId__c": "SAQQeqY100000G3t10"
      }
    }
  ]
}