{
  "Object": "PricebookEntry",
  "Fields": {
    "GearsetDisplayName": "Standard Price Book - SeededProduct24476",
    "GearsetExternalId__c": "QAQZzw4300000G3u10",
    "IsActive": "true",
    "UnitPrice": "24476.0",
    "UseStandardPrice": "false"
  },
  "References": [
    {
      "Name": "Pricebook2",
      "ReferencedObject": "Pricebook2",
      "ReferencedFields": {
        "GearsetExternalId__c": "StandardPriceBook"
      }
    },
    {
      "Name": "Product2",
      "ReferencedObject": "Product2",
      "ReferencedFields": {
        "GearsetExternalId__c": "CAQfpqY100000G3t10"
      }
    }
  ]
}